cygnusx1/__init__.py
cygnusx1/bot.py
cygnusx1/config.py
cygnusx1/downloader.py
cygnusx1/helper.py
cygnusx1/main.py
cygnusx1/scraper.py
CygnusX1-1.0.4.dist-info/METADATA
CygnusX1-1.0.4.dist-info/WHEEL
CygnusX1-1.0.4.dist-info/entry_points.txt
CygnusX1-1.0.4.dist-info/top_level.txt
CygnusX1-1.0.4.dist-info/RECORD
