Metadata-Version: 2.1
Name: CygnusX1
Version: 1.0.4
Summary: A multithreaded tool for searching and downloading images from popular search engines. It is straightforward to set up and run!
Home-page: https://github.com/datnnt1997/CygnusX1
Author: DatNgo
Author-email: datnnt97@gmail.com
License: MIT
Platform: UNKNOWN
Classifier: License :: OSI Approved :: MIT License
Classifier: Programming Language :: Python :: 3
Classifier: Programming Language :: Python :: 3.8
Requires-Dist: selenium (==3.141.0)
Requires-Dist: webdriver-manager (==3.5.1)
Requires-Dist: validators (~=0.18.2)
Requires-Dist: requests (~=2.26.0)
Requires-Dist: tqdm (==4.62.3)
